web_monitoring_diff/__init__.py
web_monitoring_diff/_version.py
web_monitoring_diff/basic_diffs.py
web_monitoring_diff/content_type.py
web_monitoring_diff/exceptions.py
web_monitoring_diff/html_links_diff.py
web_monitoring_diff/html_render_diff.py
web_monitoring_diff/utils.py
web_monitoring_diff/example_data/add-list.after
web_monitoring_diff/example_data/add-list.before
web_monitoring_diff/example_data/add-paragraph.after
web_monitoring_diff/example_data/add-paragraph.before
web_monitoring_diff/example_data/change-href.after
web_monitoring_diff/example_data/change-href.before
web_monitoring_diff/example_data/change-link-text.after
web_monitoring_diff/example_data/change-link-text.before
web_monitoring_diff/example_data/change-list-href.after
web_monitoring_diff/example_data/change-list-href.before
web_monitoring_diff/example_data/change-list-text.after
web_monitoring_diff/example_data/change-list-text.before
web_monitoring_diff/example_data/change-tag.after
web_monitoring_diff/example_data/change-tag.before
web_monitoring_diff/example_data/change-title.after
web_monitoring_diff/example_data/change-title.before
web_monitoring_diff/example_data/change-word-in-paragraph.after
web_monitoring_diff/example_data/change-word-in-paragraph.before
web_monitoring_diff/example_data/empty.pdf
web_monitoring_diff/example_data/ins-in-source.after
web_monitoring_diff/example_data/ins-in-source.before
web_monitoring_diff/example_data/remove-list.after
web_monitoring_diff/example_data/remove-list.before
web_monitoring_diff/example_data/two-paragraphs.after
web_monitoring_diff/example_data/two-paragraphs.before
web_monitoring_diff/experimental/__init__.py
web_monitoring_diff/experimental/htmldiffer.py
web_monitoring_diff/experimental/htmltreediff.py
web_monitoring_diff/server/__init__.py
web_monitoring_diff/server/server.py
web_monitoring_diff-0.1.7.data/scripts/web-monitoring-diff-server
web_monitoring_diff-0.1.7.dist-info/LICENSE
web_monitoring_diff-0.1.7.dist-info/METADATA
web_monitoring_diff-0.1.7.dist-info/WHEEL
web_monitoring_diff-0.1.7.dist-info/top_level.txt
web_monitoring_diff-0.1.7.dist-info/RECORD
