Metadata-Version: 2.1
Name: web-monitoring-diff
Version: 0.1.7
Summary: Tools for diffing & comparing web content, including a web server that generates those diffs as an HTTP service.
Home-page: https://github.com/edgi-govdata-archiving/web-monitoring-diff
Author: Environmental Data Governance Initiative
Author-email: EnviroDGI@protonmail.com
License: GPL-3.0-only
Project-URL: Documentation, https://web-monitoring-diff.readthedocs.io/en/stable/
Project-URL: Changelog, https://web-monitoring-diff.readthedocs.io/en/stable/release-history.html
Project-URL: Source code, https://github.com/edgi-govdata-archiving/web-monitoring-diff
Project-URL: Issues, https://github.com/edgi-govdata-archiving/web-monitoring-diff/issues
Classifier: Development Status :: 2 - Pre-Alpha
Classifier: Natural Language :: English
Classifier: Programming Language :: Python :: 3
Classifier: License :: OSI Approved :: GNU General Public License v3 (GPLv3)
Requires-Python: >=3.7
License-File: LICENSE
Requires-Dist: beautifulsoup4<5,>=4.9.0
Requires-Dist: fast-diff-match-patch<3,>=2.0.1
Requires-Dist: html5-parser<0.5,>=0.4.0
Requires-Dist: lxml<7,>=4.5.0
Provides-Extra: dev
Requires-Dist: coverage~=7.2; extra == "dev"
Requires-Dist: flake8~=5.0.4; extra == "dev"
Requires-Dist: pytest~=7.4.4; extra == "dev"
Provides-Extra: docs
Requires-Dist: ipython~=7.34.0; extra == "docs"
Requires-Dist: numpydoc~=1.7; extra == "docs"
Requires-Dist: sphinx~=8.1.3; extra == "docs"
Requires-Dist: sphinx-copybutton~=0.5.2; extra == "docs"
Requires-Dist: sphinx-rtd-theme~=3.0.2; extra == "docs"
Provides-Extra: server
Requires-Dist: cchardet<3,>=2.1.6; extra == "server"
Requires-Dist: pycurl<8,>=7.43; extra == "server"
Requires-Dist: sentry-sdk<2.0,>=1.0.0; extra == "server"
Requires-Dist: tornado<7,>=6.0.0; extra == "server"
